MANIFEST.in
readme.rst
setup.py
core/__init__.py
core/settings.py
core/urls.py
core/wsgi.py
django_product_catalog.egg-info/PKG-INFO
django_product_catalog.egg-info/SOURCES.txt
django_product_catalog.egg-info/dependency_links.txt
django_product_catalog.egg-info/requires.txt
django_product_catalog.egg-info/top_level.txt
product_catalog/__init__.py
product_catalog/apps.py
product_catalog/context_processors.py
product_catalog/forms.py
product_catalog/managers.py
product_catalog/settings.py
product_catalog/urls.py
product_catalog/admin/__init__.py
product_catalog/admin/category.py
product_catalog/admin/forms.py
product_catalog/admin/product.py
product_catalog/migrations/0001_initial.py
product_catalog/migrations/__init__.py
product_catalog/models/__init__.py
product_catalog/models/category.py
product_catalog/models/product.py
product_catalog/models/product_abstract.py
product_catalog/templates/layout.html
product_catalog/templates/product_catalog/_paginator.html
product_catalog/templates/product_catalog/base.html
product_catalog/templates/product_catalog/category_detail.html
product_catalog/templates/product_catalog/category_list.html
product_catalog/templates/product_catalog/home.html
product_catalog/templates/product_catalog/product_confirm_delete.html
product_catalog/templates/product_catalog/product_detail.html
product_catalog/templates/product_catalog/product_form.html
product_catalog/templates/product_catalog/product_list.html
product_catalog/templates/product_catalog/product_update_form.html
product_catalog/templates/product_catalog/tags/categories.html
product_catalog/templates/product_catalog/tags/dummy.html
product_catalog/templates/product_catalog/tags/last_products.html
product_catalog/templatetags/__init__.py
product_catalog/templatetags/product_catalog.py
product_catalog/tests/__init__.py
product_catalog/tests/test_admin_category.py
product_catalog/tests/test_admin_product.py
product_catalog/tests/test_context_processors.py
product_catalog/tests/test_managers.py
product_catalog/tests/test_models_category.py
product_catalog/tests/test_models_product.py
product_catalog/tests/test_models_product_abstract.py
product_catalog/tests/test_settings.py
